{"id":"0001","nombre":"Lur","chip":"981098104741945","talla":"M"}
{"id":"0002","nombre":"Lai","chip":"958695864741945","talla":"M"}
{"id":"0003","nombre":"Luna","chip":"123457604741945","talla":"XL"}
{"id":"0004","nombre":"Argui","chip":"981258904741945","talla":"L"}
{"id":"0005","nombre":"Choco","chip":"982555555541945","talla":"L"}
{"id":"0006","nombre":"Tobi","chip":"981077777741945","talla":"L"}
{"id":"0007","nombre":"Elur","chip":"988758894741945","talla":"L"}
{"id":"0008","nombre":"Kiwi","chip":"981091234851945","talla":"L"}
{"id":"0009","nombre":"Rambito","chip":"981015404741945","talla":"S"}
{"id":"0010","nombre":"Kara","chip":"981036522741945","talla":"S"}
{"id":"0010","nombre":"Jimbo","chip":"981785224741945","talla":"S"}
{"id":"0011","nombre":"Tronka","chip":"981091562241945","talla":"S"}
{"id":"0012","nombre":"Zeus","chip":"981036556551945","talla":"M"}
{"id":"0013","nombre":"Bimba","chip":"981025668541945","talla":"M"}
{"id":"0014","nombre":"Puma","chip":"981097412241945","talla":"M"}
{"id":"0015","nombre":"Thor","chip":"983651563521945","talla":"XL"}
{"id":"0016","nombre":"Dalton","chip":"658565258741945","talla":"XL"}
{"id":"0017","nombre":"Jack","chip":"945824654125545","talla":"L"}
{"id":"0018","nombre":"Roco","chip":"982525252525945","talla":"S"}
{"id":"0018","nombre":"Shiba","chip":"981045656541945","talla":"S"}
{"id":"0020","nombre":"Klaus","chip":"981012365485945","talla":"L"}
{"id":"0021","nombre":"Roy","chip":"981012388541945","talla":"M"}
{"id":"0022","nombre":"Kevin","chip":"933333333741945","talla":"M"}
{"id":"0023","nombre":"Troy","chip":"987777774741945","talla":"M"}
{"id":"0024","nombre":"Nala","chip":"981095555581945","talla":"S"}
{"id":"0025","nombre":"Kala","chip":"981066666641945","talla":"XL"}
{"id":"0026","nombre":"Dylan","chip":"981083216595945","talla":"L"}
{"id":"0027","nombre":"Negro","chip":"981011111111945","talla":"L"}
{"id":"0028","nombre":"Can","chip":"982222222241945","talla":"S"}
{"id":"0029","nombre":"Bolt","chip":"981033352521945","talla":"L"}
{"id":"0030","nombre":"Mini","chip":"977777777777945","talla":"XL"}